setup.py
logreplay/__init__.py
logreplay/config.py
logreplay/core.py
logreplay/events.py
logreplay/main.py
logreplay/model.py
logreplay/monitor.py
logreplay/parser.py
logreplay.egg-info/PKG-INFO
logreplay.egg-info/SOURCES.txt
logreplay.egg-info/dependency_links.txt
logreplay.egg-info/requires.txt
logreplay.egg-info/top_level.txt