Metadata-Version: 1.1
Name: logreplay
Version: 0.2.0
Summary: a log-based tool to replay http requests
Home-page: https://github.com/jacexh/log-replay
Author: jace
Author-email: jace@xuh.me
License: MIT
Platform: UNKNOWN
Classifier: Development Status :: 5 - Production/Stable
Classifier: Intended Audience :: Developers
Classifier: License :: OSI Approved :: MIT License
Classifier: Programming Language :: Python :: 3.5
